MANIFEST.in
setup.cfg
setup.py
django_templates_admin/__init__.py
django_templates_admin.egg-info/PKG-INFO
django_templates_admin.egg-info/SOURCES.txt
django_templates_admin.egg-info/dependency_links.txt
django_templates_admin.egg-info/not-zip-safe
django_templates_admin.egg-info/top_level.txt
django_templates_admin/templates/__init__.py
django_templates_admin/templates/admin.py
django_templates_admin/templates/models.py
django_templates_admin/templates/templates/admin/templates/change_form.html