Metadata-Version: 1.0
Name: django-templates-admin
Version: 0.4.1
Summary: Edit project template files from the Django admin UI
Home-page: https://github.com/IlyaSemenov/django-templates-admin
Author: Ilya Semenov
Author-email: ilya@semenov.co
License: BSD
Platform: any
